{
    "general Mobile Phone": {
        "standard": true,
        "properties": {
            "Device_Name": "general Mobile Phone",
            "Device_Maker": "unknown",
            "Device_Type": "Mobile Phone",
            "Device_Pointing_Method": "unknown",
            "Device_Code_Name": "general Mobile Phone",
            "Device_Brand_Name": "unknown",
            "isMobileDevice": "true",
            "isTablet": "false"
        }
    },
    "general Mobile Phone (Touch)": {
        "standard": true,
        "properties": {
            "Device_Name": "general Mobile Phone",
            "Device_Maker": "unknown",
            "Device_Type": "Mobile Phone",
            "Device_Pointing_Method": "touchscreen",
            "Device_Code_Name": "general Mobile Phone",
            "Device_Brand_Name": "unknown",
            "isMobileDevice": "true",
            "isTablet": "false"
        }
    }
}