{
  "Acer DA241HL": {
    "type": "desktop",
    "properties": {
      "Device_Name": "DA 241HL",
      "Device_Code_Name": "DA241HL",
      "Device_Maker": "Acer",
      "Device_Pointing_Method": "mouse",
      "Device_Brand_Name": "Acer"
    },
    "standard": true
  },
  "Acer CB3-431": {
    "type": "desktop",
    "properties": {
      "Device_Name": "Chromebook 14",
      "Device_Code_Name": "CB3-431",
      "Device_Maker": "Acer",
      "Device_Pointing_Method": "mouse",
      "Device_Brand_Name": "Acer"
    },
    "standard": true
  },
  "Acer CB5-312T": {
    "type": "desktop",
    "properties": {
      "Device_Name": "Chromebook R13",
      "Device_Code_Name": "CB5-312T",
      "Device_Maker": "Acer",
      "Device_Pointing_Method": "mouse",
      "Device_Brand_Name": "Acer"
    },
    "standard": true
  },
  "Acer CB5-132T": {
    "type": "desktop",
    "properties": {
      "Device_Name": "Chromebook R11",
      "Device_Code_Name": "CB5-132T",
      "Device_Maker": "Acer",
      "Device_Pointing_Method": "mouse",
      "Device_Brand_Name": "Acer"
    },
    "standard": true
  }
}
